Metadata-Version: 2.1
Name: FantasyNomes
Version: 1.0
Summary: UNKNOWN
Home-page: UNKNOWN
Author: 
Author-email: 
Maintainer: 
Maintainer-email: 
License: Apache 2.0
Keywords: FantasyNomes
Platform: UNKNOWN
Classifier: Development Status :: 4 - Beta
Classifier: Environment :: Console
Classifier: Framework :: Jupyter :: JupyterLab
Classifier: License :: OSI Approved :: Apache Software License
Classifier: Natural Language :: English
Classifier: Programming Language :: Python
Classifier: Programming Language :: Python :: 3
Classifier: Operating System :: OS Independent
Classifier: Intended Audience :: Developers
Classifier: Topic :: Education
Classifier: Topic :: Scientific/Engineering :: Mathematics
Requires-Python: >=3.7
License-File: LICENSE
